mitmproxy_macos/__init__.py
mitmproxy_macos/macos-certificate-truster.app/Contents/Info.plist
mitmproxy_macos/macos-certificate-truster.app/Contents/Resources/mitmproxy.icns
version-info.toml
mitmproxy_macos/Mitmproxy Redirector.app.tar
mitmproxy_macos-0.12.9.dist-info/METADATA
mitmproxy_macos-0.12.9.dist-info/WHEEL
mitmproxy_macos-0.12.9.dist-info/RECORD
