Metadata-Version: 2.4
Name: mitmproxy-macos
Version: 0.12.9
Project-URL: Source, https://github.com/mitmproxy/mitmproxy-rs
License-Expression: MIT
Requires-Python: >=3.12
